NiukeDujiaChunzhaoShixiBeizhanShouceJishuPian20202021/README.md
NiukeDujiaChunzhaoShixiBeizhanShouceJishuPian20202021/__init__.py
NiukeDujiaChunzhaoShixiBeizhanShouceJishuPian20202021/__main__.py
NiukeDujiaChunzhaoShixiBeizhanShouceJishuPian20202021/file.pdf
NiukeDujiaChunzhaoShixiBeizhanShouceJishuPian20202021/index.html
niuke_dujia_chunzhao_shixi_beizhan_shouce_jishu_pian_2020_2021-2024.3.5.0.dist-info/METADATA
niuke_dujia_chunzhao_shixi_beizhan_shouce_jishu_pian_2020_2021-2024.3.5.0.dist-info/WHEEL
niuke_dujia_chunzhao_shixi_beizhan_shouce_jishu_pian_2020_2021-2024.3.5.0.dist-info/entry_points.txt
niuke_dujia_chunzhao_shixi_beizhan_shouce_jishu_pian_2020_2021-2024.3.5.0.dist-info/top_level.txt
niuke_dujia_chunzhao_shixi_beizhan_shouce_jishu_pian_2020_2021-2024.3.5.0.dist-info/RECORD
